{
  "kind": "singleType",
  "collectionName": "homepages",
  "info": {
    "singularName": "homepage",
    "pluralName": "homepages",
    "displayName": "Homepage",
    "description": ""
  },
  "options": {},
  "pluginOptions": {},
  "attributes": {
    "heroTitle": {
      "type": "string"
    },
    "heroSubtitle": {
      "type": "text"
    },
    "heroDescription": {
      "type": "text"
    },
    "heroPrimaryCtaLabel": {
      "type": "string"
    },
    "heroPrimaryCtaUrl": {
      "type": "string"
    },
    "heroSecondaryCtaLabel": {
      "type": "string"
    },
    "heroSecondaryCtaUrl": {
      "type": "string"
    },
    "heroBackground": {
      "type": "media"
    },
    "valuesTitle": {
      "type": "string"
    },
    "valuesIntro": {
      "type": "text"
    },
    "values": {
      "component": "shared.value",
      "repeatable": true,
      "type": "component"
    },
    "aboutTitle": {
      "type": "string"
    },
    "aboutIntro": {
      "type": "richtext"
    },
    "aboutMissionTitle": {
      "type": "string"
    },
    "aboutMissionDescription": {
      "type": "text"
    },
    "aboutMissions": {
      "component": "shared.value",
      "repeatable": true,
      "type": "component"
    },
    "aboutMainStats": {
      "component": "shared.stat-item",
      "repeatable": true,
      "type": "component"
    },
    "aboutImage1": {
      "type": "media"
    },
    "aboutImage2": {
      "type": "media"
    },
    "aboutCtaLabel": {
      "type": "string"
    },
    "aboutCtaUrl": {
      "type": "string"
    },
    "domainsTitle": {
      "type": "string"
    },
    "domainsSubtitle": {
      "type": "text"
    },
    "domainsDescription": {
      "type": "text"
    },
    "domainsImage": {
      "type": "media"
    },
    "highlightedDomains": {
      "type": "relation",
      "relation": "oneToMany",
      "target": "api::domain.domain"
    },
    "domainsCtaLabel": {
      "type": "string"
    },
    "domainsCtaUrl": {
      "type": "string"
    },
    "eventsTitle": {
      "type": "string"
    },
    "eventsSubtitle": {
      "type": "string"
    },
    "highlightedEvents": {
      "type": "relation",
      "relation": "oneToMany",
      "target": "api::activity.activity"
    },
    "contributeTitle": {
      "type": "string"
    },
    "contributeSubtitle": {
      "type": "string"
    },
    "contributeDescription": {
      "type": "text"
    },
    "contributeStats": {
      "component": "shared.stat-item",
      "repeatable": true,
      "type": "component"
    },
    "contributePrimaryCtaLabel": {
      "type": "string"
    },
    "contributePrimaryCtaUrl": {
      "type": "string"
    },
    "contributeSecondaryCtaLabel": {
      "type": "string"
    },
    "contributeSecondaryCtaUrl": {
      "type": "string"
    },
    "galleryTitle": {
      "type": "string"
    },
    "gallerySubtitle": {
      "type": "string"
    },
    "galleryHighlightMedia": {
      "type": "relation",
      "relation": "oneToMany",
      "target": "api::media-item.media-item"
    },
    "partnersTitle": {
      "type": "string"
    },
    "partnersSubtitle": {
      "type": "string"
    },
    "highlightedPartners": {
      "type": "relation",
      "relation": "oneToMany",
      "target": "api::partner.partner"
    }
  }
}